LICENSE
axie_utils/__init__.py
axie_utils/abis.py
axie_utils/axies.py
axie_utils/breeding.py
axie_utils/claims.py
axie_utils/graphql.py
axie_utils/morphing.py
axie_utils/payments.py
axie_utils/scatter.py
axie_utils/transfers.py
axie_utils/utils.py
axie_utils-2.1.3.dist-info/LICENSE
axie_utils-2.1.3.dist-info/WHEEL
axie_utils-2.1.3.dist-info/METADATA
axie_utils-2.1.3.dist-info/RECORD
