Metadata-Version: 2.1
Name: axie-utils
Version: 2.1.3
Summary: Library that provides the functionality you need to build your own axie Infinity python tools
Home-page: https://ferranmarin.github.io/axie-utils-lib/
License: GNU LGPLv3
Keywords: axie,axie infinity,tools,utils,ronin,ronin chain
Author: Ferran Marin
Author-email: ferran.marin.llobet@gmail.com
Requires-Python: >=3.8,<4.0
Classifier: Development Status :: 5 - Production/Stable
Classifier: Environment :: Console
Classifier: Intended Audience :: Developers
Classifier: Intended Audience :: Education
Classifier: License :: OSI Approved :: GNU Lesser General Public License v3 (LGPLv3)
Classifier: License :: Other/Proprietary License
Classifier: Operating System :: OS Independent
Classifier: Programming Language :: Python
Classifier: Programming Language :: Python :: 3
Classifier: Programming Language :: Python :: 3.8
Classifier: Programming Language :: Python :: 3.9
Classifier: Programming Language :: Python :: 3.10
Classifier: Topic :: Games/Entertainment
Classifier: Topic :: Software Development :: Libraries
Requires-Dist: trezor[hidapi] (>=0.13.0,<0.14.0)
Requires-Dist: web3 (>=5.25.0,<6.0.0)
Project-URL: Repository, https://github.com/FerranMarin/axie-utils-lib
